openehr_am/AGENTS.md
openehr_am/__about__.py
openehr_am/__init__.py
openehr_am/py.typed
openehr_am/_generated/AqlLexer.interp
openehr_am/_generated/AqlLexer.py
openehr_am/_generated/AqlLexer.tokens
openehr_am/_generated/AqlParser.interp
openehr_am/_generated/AqlParser.py
openehr_am/_generated/AqlParser.tokens
openehr_am/_generated/AqlParserListener.py
openehr_am/_generated/AqlParserVisitor.py
openehr_am/_generated/OpenEHRPath.interp
openehr_am/_generated/OpenEHRPath.tokens
openehr_am/_generated/OpenEHRPathLexer.interp
openehr_am/_generated/OpenEHRPathLexer.py
openehr_am/_generated/OpenEHRPathLexer.tokens
openehr_am/_generated/OpenEHRPathListener.py
openehr_am/_generated/OpenEHRPathParser.py
openehr_am/_generated/OpenEHRPathVisitor.py
openehr_am/_generated/README.md
openehr_am/_generated/__init__.py
openehr_am/adl/__init__.py
openehr_am/adl/ast.py
openehr_am/adl/cadl_ast.py
openehr_am/adl/expr_ast.py
openehr_am/adl/expr_parser.py
openehr_am/adl/parser.py
openehr_am/antlr/__init__.py
openehr_am/antlr/runtime.py
openehr_am/antlr/span.py
openehr_am/aom/__init__.py
openehr_am/aom/archetype.py
openehr_am/aom/builder.py
openehr_am/aom/constraints.py
openehr_am/aom/debug_dict.py
openehr_am/aom/ids.py
openehr_am/aom/repository.py
openehr_am/aom/terminology.py
openehr_am/aql/__init__.py
openehr_am/aql/parser.py
openehr_am/bmm/__init__.py
openehr_am/bmm/loader.py
openehr_am/bmm/model.py
openehr_am/bmm/repository.py
openehr_am/cli/__init__.py
openehr_am/cli/app.py
openehr_am/cli/main.py
openehr_am/cli/render.py
openehr_am/odin/__init__.py
openehr_am/odin/ast.py
openehr_am/odin/emit.py
openehr_am/odin/parser.py
openehr_am/odin/transformer.py
openehr_am/opt/__init__.py
openehr_am/opt/compiler.py
openehr_am/opt/debug_dict.py
openehr_am/opt/dependencies.py
openehr_am/opt/flattening.py
openehr_am/opt/json.py
openehr_am/opt/model.py
openehr_am/path/__init__.py
openehr_am/path/ast.py
openehr_am/path/parser.py
openehr_am/path/resolver.py
openehr_am/validation/__init__.py
pyopenehr_am-0.0.3.dist-info/METADATA
pyopenehr_am-0.0.3.dist-info/WHEEL
pyopenehr_am-0.0.3.dist-info/entry_points.txt
pyopenehr_am-0.0.3.dist-info/licenses/LICENSE
pyopenehr_am-0.0.3.dist-info/RECORD
