Metadata-Version: 2.4
Name: pyopenehr-am
Version: 0.0.3
Summary: Pure-Python openEHR AM toolkit (ADL2/AOM2/ODIN/BMM/OPT2).
Project-URL: Homepage, https://github.com/rubentalstra/pyopenehr-am
Project-URL: Repository, https://github.com/rubentalstra/pyopenehr-am
Project-URL: Source, https://github.com/rubentalstra/pyopenehr-am.git
Project-URL: Issues, https://github.com/rubentalstra/pyopenehr-am/issues
Project-URL: Documentation, https://github.com/rubentalstra/pyopenehr-am/tree/main/docs
Project-URL: Changelog, https://github.com/rubentalstra/pyopenehr-am/releases
Project-URL: Security, https://github.com/rubentalstra/pyopenehr-am/blob/main/SECURITY.md
Project-URL: PyPI, https://pypi.org/project/pyopenehr-am/
Author: Ruben Talstra
License: MIT License
License-File: LICENSE
Keywords: ADL2,AOM2,BMM,ODIN,OPT2,ehr,health,openEHR
Classifier: Development Status :: 3 - Alpha
Classifier: Intended Audience :: Developers
Classifier: License :: OSI Approved :: MIT License
Classifier: Programming Language :: Python :: 3 :: Only
Classifier: Programming Language :: Python :: 3.14
Classifier: Topic :: Scientific/Engineering :: Medical Science Apps.
Classifier: Topic :: Software Development :: Libraries
Classifier: Typing :: Typed
Requires-Python: >=3.14
Requires-Dist: antlr4-python3-runtime==4.13.2
Requires-Dist: rich>=14.2.0
Requires-Dist: typer>=0.20.0
Provides-Extra: dev
Requires-Dist: antlr4-tools>=0.2.2; extra == 'dev'
Requires-Dist: pre-commit>=4.5.1; extra == 'dev'
Requires-Dist: pyright>=1.1.407; extra == 'dev'
Requires-Dist: pytest-cov>=7.0.0; extra == 'dev'
Requires-Dist: pytest>=9.0.2; extra == 'dev'
Requires-Dist: ruff>=0.14.10; extra == 'dev'
Provides-Extra: release
Requires-Dist: build==1.3.0; extra == 'release'
Requires-Dist: twine==6.2.0; extra == 'release'
